[{"birthdate":"16/01/1997","isBlock":true,"injuredDays":0,"photo2":"0000564098_5-6_03.jpg","isActive":true,"idTeam":2,"statusTeamSquad":"normal","nick":"Barreiro","number":7,"insertDatetime":"20240909T093356+0000","price":251275.0,"height":"203","isNational":true,"isExitLeague":false,"initialPrice":190000.0,"fullName":"Jonathan Barreiro","photo":"0000564081_5-6_03.jpg","url":"https://www.acb.com/jugador/todos-sus-partidos/id/20200191","fisicStatus":"fit","imageTeam":"2324UnicajaLogo.png","license":"JFL","idPlayer":26,"birthplace":"Cerceda (A Coruña)","nationality":"España","competitionAverage":6.6,"playerStats":[{"pointsJourney":8.4,"numberJourney":3},{"pointsJourney":6.0,"numberJourney":2},{"pointsJourney":7.2,"numberJourney":1}],"imageTeamNegative":"2324UnicajaLogo.png","position":3,"isExtraCommunity":false,"shortName":"J. Barreiro","nameTeam":"Unicaja","age":27},{"birthdate":"02/04/1989","injuredDays":0,"photo2":"0000564894_5-6_03.jpg","isActive":true,"idTeam":7,"statusTeamSquad":"normal","nick":"Shermadini","number":19,"insertDatetime":"20240909T093402+0000","price":680000.0,"height":"217","isNational":false,"isExitLeague":false,"initialPrice":800000.0,"fullName":"Giorgi Shermadini","photo":"0000564886_5-6_03.jpg","url":"https://www.acb.com/jugador/todos-sus-partidos/id/20210659","fisicStatus":"fit","imageTeam":"2425LaLagunaTenerifeLogo.png","license":"EUR","idPlayer":54,"birthplace":"Mtskheta","nationality":"Georgia","competitionAverage":8.4,"playerStats":[{"teamNegative":"2324BarcaLogoweb.png","numberJourney":3,"team":"2324BarcaLogoweb.png","isLocal":true},{"numberJourney":2},{"pointsJourney":8.4,"numberJourney":1}],"imageTeamNegative":"2425LaLagunaTenerifeLogoneg.png","position":5,"isExtraCommunity":false,"shortName":"G. Shermadini","nameTeam":"La Laguna Tenerife","age":35},{"birthdate":"27/05/1997","isBlock":true,"injuredDays":0,"photo2":"0000568863_5-6_03.jpg","isActive":true,"idTeam":13,"statusTeamSquad":"normal","nick":"Frey","number":3,"insertDatetime":"20240909T093411+0000","price":515775.0,"height":"188","isNational":false,"isExitLeague":false,"initialPrice":390000.0,"fullName":"Harald Frey","photo":"0000568845_5-6_03.jpg","url":"https://www.acb.com/jugador/todos-sus-partidos/id/30003398","fisicStatus":"fit","imageTeam":"logo_surnebb_pos.png","license":"EUR","idPlayer":103,"birthplace":"Oslo","nationality":"Noruega","competitionAverage":14.6,"playerStats":[{"pointsJourney":9.6,"numberJourney":3},{"pointsJourney":16.0,"numberJourney":2},{"pointsJourney":13.2,"numberJourney":1}],"imageTeamNegative":"logo_surnebb_neg.png","position":1,"isExtraCommunity":false,"shortName":"H. Frey","nameTeam":"Surne Bilbao Basket","age":27},{"birthdate":"25/05/1999","isBlock":true,"injuredDays":0,"photo2":"0000568911_5-6_03.jpg","isActive":true,"idTeam":13,"statusTeamSquad":"normal","nick":"Kullamae","number":77,"insertDatetime":"20240909T093411+0000","price":409975.0,"height":"193","isNational":false,"isExitLeague":false,"initialPrice":310000.0,"fullName":"Kristian Kullamae","photo":"0000568902_5-6_03.jpg","url":"https://www.acb.com/jugador/todos-sus-partidos/id/30001225","fisicStatus":"fit","imageTeam":"logo_surnebb_pos.png","license":"EUR","idPlayer":107,"birthplace":"Tallin","nationality":"Estonia","competitionAverage":9.0,"playerStats":[{"pointsJourney":22.8,"numberJourney":3},{"pointsJourney":6.0,"numberJourney":2},{"pointsJourney":12.0,"numberJourney":1}],"imageTeamNegative":"logo_surnebb_neg.png","position":3,"isExtraCommunity":false,"shortName":"K. Kullamae","nameTeam":"Surne Bilbao Basket","age":25},{"birthdate":"01/09/1994","isBlock":true,"injuredDays":0,"photo2":"0000568998_5-6_03.jpg","isActive":true,"idTeam":13,"statusTeamSquad":"normal","nick":"A.-Rahkman","number":5,"insertDatetime":"20240909T093411+0000","price":502550.0,"height":"196","isNational":false,"isExitLeague":false,"initialPrice":380000.0,"fullName":"Muhammad-Ali Abdur-Rahkman","photo":"0000569003_5-6_03.jpg","url":"https://www.acb.com/jugador/todos-sus-partidos/id/30003400","fisicStatus":"fit","imageTeam":"logo_surnebb_pos.png","license":"EXT","idPlayer":108,"birthplace":"Pensilvania","nationality":"EE.UU.","competitionAverage":21.9,"playerStats":[{"pointsJourney":-3.0,"numberJourney":3},{"pointsJourney":21.0,"numberJourney":2},{"pointsJourney":22.8,"numberJourney":1}],"imageTeamNegative":"logo_surnebb_neg.png","position":3,"isExtraCommunity":true,"shortName":"Abdur-Rahkman","nameTeam":"Surne Bilbao Basket","age":30},{"birthdate":"10/04/2000","isBlock":true,"injuredDays":0,"photo2":"0000568967_5-6_03.jpg","isActive":true,"idTeam":13,"statusTeamSquad":"normal","nick":"Pantzar","number":19,"insertDatetime":"20240909T093411+0000","price":700925.0,"height":"190","isNational":true,"isExitLeague":false,"initialPrice":530000.0,"fullName":"Melwin Pantzar","photo":"0000568953_5-6_03.jpg","url":"https://www.acb.com/jugador/todos-sus-partidos/id/20212357","fisicStatus":"fit","imageTeam":"logo_surnebb_pos.png","license":"JFL","idPlayer":112,"birthplace":"Valsta","nationality":"Suecia","competitionAverage":17.0,"playerStats":[{"pointsJourney":13.2,"numberJourney":3},{"pointsJourney":16.0,"numberJourney":2},{"pointsJourney":18.0,"numberJourney":1}],"imageTeamNegative":"logo_surnebb_neg.png","position":1,"isExtraCommunity":false,"shortName":"M. Pantzar","nameTeam":"Surne Bilbao Basket","age":24},{"birthdate":"03/01/1994","isBlock":true,"injuredDays":0,"photo2":"0000571147_5-6_03.jpg","isActive":true,"idTeam":17,"statusTeamSquad":"normal","nick":"Burjanadze","number":77,"insertDatetime":"20240909T093414+0000","price":370300.0,"height":"201","isNational":true,"isExitLeague":false,"initialPrice":280000.0,"fullName":"Beqa Burjanadze","photo":"0000571133_5-6_03.jpg","url":"https://www.acb.com/jugador/todos-sus-partidos/id/20204145","fisicStatus":"fit","imageTeam":"2425BCoruna.png","license":"JFL","idPlayer":145,"birthplace":"Tbilisi","nationality":"Georgia","competitionAverage":10.3,"playerStats":[{"pointsJourney":11.0,"numberJourney":3},{"pointsJourney":11.0,"numberJourney":2},{"pointsJourney":9.6,"numberJourney":1}],"imageTeamNegative":"2425BCoruna.png","position":5,"isExtraCommunity":false,"shortName":"B. Burjanadze","nameTeam":"Leyma Coruña","age":30},{"birthdate":"24/12/1995","isBlock":true,"injuredDays":0,"photo2":"0000567691_5-6_03.jpg","isActive":true,"idTeam":6,"statusTeamSquad":"normal","nick":"Moneke","number":95,"insertDatetime":"20240909T150133+0000","price":1025000.0,"height":"198","isNational":false,"isExitLeague":false,"initialPrice":950000.0,"fullName":"Chima Moneke","photo":"0000567667_5-6_03.jpg","url":"https://www.acb.com/jugador/todos-sus-partidos/id/30001128","fisicStatus":"fit","imageTeam":"baskonia_00.png","license":"COT","idPlayer":170,"birthplace":"Abuja","nationality":"Nigeria","competitionAverage":20.5,"playerStats":[{"pointsJourney":16.8,"numberJourney":3},{"pointsJourney":19.0,"numberJourney":2},{"pointsJourney":22.0,"numberJourney":1}],"imageTeamNegative":"baskonia_00.png","position":5,"isExtraCommunity":false,"shortName":"C. Moneke","nameTeam":"Baskonia","age":28},{"birthdate":"15/01/2002","isBlock":true,"injuredDays":0,"photo2":"0000567798_5-6_03.jpg","isActive":true,"idTeam":6,"statusTeamSquad":"normal","nick":"Diop","number":18,"insertDatetime":"20240909T150134+0000","price":225000.0,"height":"215","isNational":true,"isExitLeague":false,"initialPrice":280000.0,"fullName":"Khalifa Diop","photo":"0000567786_5-6_03.jpg","url":"https://www.acb.com/jugador/todos-sus-partidos/id/20212905","fisicStatus":"fit","imageTeam":"baskonia_00.png","license":"JFL","idPlayer":179,"birthplace":"Guediawaye","nationality":"Senegal","competitionAverage":4.5,"playerStats":[{"pointsJourney":-3.0,"numberJourney":3},{"pointsJourney":6.0,"numberJourney":2},{"pointsJourney":3.0,"numberJourney":1}],"imageTeamNegative":"baskonia_00.png","position":5,"isExtraCommunity":false,"shortName":"K. Diop","nameTeam":"Baskonia","age":22},{"birthdate":"03/03/1999","isBlock":true,"injuredDays":0,"photo2":"0000567855_5-6_03.jpg","isActive":true,"idTeam":6,"statusTeamSquad":"normal","nick":"Howard","number":0,"insertDatetime":"20240909T150134+0000","price":484075.0,"height":"179","isNational":false,"isExitLeague":false,"initialPrice":670000.0,"fullName":"Markus Howard","photo":"0000567839_5-6_03.jpg","url":"https://www.acb.com/jugador/todos-sus-partidos/id/30001957","fisicStatus":"fit","imageTeam":"baskonia_00.png","license":"EXT","idPlayer":180,"birthplace":"New Jersey","nationality":"EE.UU.","competitionAverage":2.5,"playerStats":[{"pointsJourney":8.4,"numberJourney":3},{"pointsJourney":9.0,"numberJourney":2},{"pointsJourney":-4.0,"numberJourney":1}],"imageTeamNegative":"baskonia_00.png","position":3,"isExtraCommunity":true,"shortName":"M. Howard","nameTeam":"Baskonia","age":25}]